{
  "app_status": {
    "FloodClaims Pro": {
      "status": "up",
      "http_code": 200,
      "response_ms": 408.2,
      "last_check": "2026-05-29T05-36-09Z"
    },
    "AI Agent Widget": {
      "status": "up",
      "http_code": 200,
      "response_ms": 205.9,
      "last_check": "2026-05-29T04-44-08Z"
    },
    "EcDash": {
      "status": "up",
      "http_code": 200,
      "response_ms": 253.4,
      "last_check": "2026-05-29T05-36-11Z"
    },
    "Liberty Oil": {
      "status": "up",
      "http_code": 200,
      "response_ms": 479.5,
      "last_check": "2026-05-29T05-36-27Z"
    },
    "Sweet Spot Cakes": {
      "status": "up",
      "http_code": 200,
      "response_ms": 263.1,
      "last_check": "2026-05-29T05-36-09Z"
    },
    "Remote Repair": {
      "status": "up",
      "http_code": 200,
      "response_ms": 311.8,
      "last_check": "2026-05-29T05-36-09Z"
    },
    "Agents": {
      "status": "up",
      "http_code": 200,
      "response_ms": 228.2,
      "last_check": "2026-05-29T05-36-09Z"
    },
    "Shop": {
      "status": "up",
      "http_code": 200,
      "response_ms": 232.6,
      "last_check": "2026-05-29T05-36-10Z"
    },
    "Voice Makeover": {
      "status": "up",
      "http_code": 200,
      "response_ms": 212.5,
      "last_check": "2026-05-29T05-36-10Z"
    },
    "AI Widget": {
      "status": "up",
      "http_code": 200,
      "response_ms": 223.1,
      "last_check": "2026-05-29T05-36-10Z"
    },
    "Consignment": {
      "status": "up",
      "http_code": 200,
      "response_ms": 231.4,
      "last_check": "2026-05-29T05-36-10Z"
    },
    "Contractor Pro": {
      "status": "down",
      "http_code": 0,
      "response_ms": 224.0,
      "last_check": "2026-05-29T05-36-11Z"
    },
    "Pet Vet AI": {
      "status": "up",
      "http_code": 200,
      "response_ms": 251.6,
      "last_check": "2026-05-29T05-36-11Z"
    },
    "LE Thrift": {
      "status": "up",
      "http_code": 200,
      "response_ms": 709.8,
      "last_check": "2026-05-29T05-36-12Z"
    },
    "Gym Forge": {
      "status": "down",
      "http_code": 0,
      "response_ms": 15188.4,
      "last_check": "2026-05-29T05-36-27Z"
    },
    "Luxury Rentals Demo": {
      "status": "up",
      "http_code": 200,
      "response_ms": 258.1,
      "last_check": "2026-05-29T05-36-28Z"
    },
    "Inventory Demo": {
      "status": "up",
      "http_code": 200,
      "response_ms": 260.2,
      "last_check": "2026-05-29T05-36-28Z"
    },
    "IT Courses": {
      "status": "up",
      "http_code": 200,
      "response_ms": 232.7,
      "last_check": "2026-05-29T05-36-28Z"
    }
  },
  "alert_cooldown": {
    "Liberty Oil": 1780028530.7740707,
    "Contractor Pro": 1780032146.2935965,
    "Gym Forge": 1780032146.2935965,
    "FloodClaims Pro": 1780032339.8295178
  }
}