{
  "app_status": {
    "FloodClaims Pro": {
      "status": "up",
      "http_code": 200,
      "response_ms": 445.4,
      "last_check": "2026-05-30T00-20-11Z"
    },
    "AI Agent Widget": {
      "status": "up",
      "http_code": 200,
      "response_ms": 205.9,
      "last_check": "2026-05-29T04-44-08Z"
    },
    "EcDash": {
      "status": "up",
      "http_code": 200,
      "response_ms": 247.4,
      "last_check": "2026-05-30T00-20-14Z"
    },
    "Liberty Oil": {
      "status": "up",
      "http_code": 200,
      "response_ms": 356.8,
      "last_check": "2026-05-30T00-20-30Z"
    },
    "Sweet Spot Cakes": {
      "status": "up",
      "http_code": 200,
      "response_ms": 200.8,
      "last_check": "2026-05-30T00-20-11Z"
    },
    "Remote Repair": {
      "status": "up",
      "http_code": 200,
      "response_ms": 215.2,
      "last_check": "2026-05-30T00-20-11Z"
    },
    "Agents": {
      "status": "up",
      "http_code": 200,
      "response_ms": 281.1,
      "last_check": "2026-05-30T00-20-12Z"
    },
    "Shop": {
      "status": "up",
      "http_code": 200,
      "response_ms": 219.5,
      "last_check": "2026-05-30T00-20-12Z"
    },
    "Voice Makeover": {
      "status": "up",
      "http_code": 200,
      "response_ms": 279.4,
      "last_check": "2026-05-30T00-20-12Z"
    },
    "AI Widget": {
      "status": "up",
      "http_code": 200,
      "response_ms": 1284.7,
      "last_check": "2026-05-30T00-20-13Z"
    },
    "Consignment": {
      "status": "up",
      "http_code": 200,
      "response_ms": 240.3,
      "last_check": "2026-05-30T00-20-14Z"
    },
    "Contractor Pro": {
      "status": "down",
      "http_code": 0,
      "response_ms": 210.0,
      "last_check": "2026-05-30T00-20-14Z"
    },
    "Pet Vet AI": {
      "status": "up",
      "http_code": 200,
      "response_ms": 231.4,
      "last_check": "2026-05-30T00-20-14Z"
    },
    "LE Thrift": {
      "status": "up",
      "http_code": 200,
      "response_ms": 556.1,
      "last_check": "2026-05-30T00-20-15Z"
    },
    "Gym Forge": {
      "status": "down",
      "http_code": 0,
      "response_ms": 15204.8,
      "last_check": "2026-05-30T00-20-30Z"
    },
    "Luxury Rentals Demo": {
      "status": "up",
      "http_code": 200,
      "response_ms": 199.9,
      "last_check": "2026-05-30T00-20-31Z"
    },
    "Inventory Demo": {
      "status": "up",
      "http_code": 200,
      "response_ms": 250.4,
      "last_check": "2026-05-30T00-20-31Z"
    },
    "IT Courses": {
      "status": "up",
      "http_code": 200,
      "response_ms": 204.5,
      "last_check": "2026-05-30T00-20-31Z"
    }
  },
  "alert_cooldown": {
    "Liberty Oil": 1780028530.7740707,
    "Contractor Pro": 1780032146.2935965,
    "Gym Forge": 1780032146.2935965,
    "FloodClaims Pro": 1780089350.2159703
  }
}